examples/instances.py
examples/models.py
examples/variants.py
examples/conversion/rvc2.py
examples/conversion/rvc2_legacy.py
examples/conversion/rvc4_fp16.py
examples/conversion/rvc4_int8.py
examples/conversion/yolo.py
hubai_sdk/__init__.py
hubai_sdk/__main__.py
hubai_sdk/hubai_client.py
hubai_sdk/typing.py
hubai_sdk/services/__init__.py
hubai_sdk/services/convert.py
hubai_sdk/services/instances.py
hubai_sdk/services/models.py
hubai_sdk/services/variants.py
hubai_sdk/utils/__init__.py
hubai_sdk/utils/config.py
hubai_sdk/utils/constants.py
hubai_sdk/utils/environ.py
hubai_sdk/utils/filesystem_utils.py
hubai_sdk/utils/general.py
hubai_sdk/utils/hub.py
hubai_sdk/utils/hub_requests.py
hubai_sdk/utils/hubai_models.py
hubai_sdk/utils/layout.py
hubai_sdk/utils/metadata.py
hubai_sdk/utils/nn_archive.py
hubai_sdk/utils/sdk_models.py
hubai_sdk/utils/subprocess.py
hubai_sdk/utils/telemetry.py
hubai_sdk/utils/types.py
hubai_sdk-0.2.0.dist-info/licenses/LICENSE
scripts/fix_nullable.py
tests/__init__.py
tests/conftest.py
tests/test_instances.py
tests/test_models.py
tests/test_variants.py
tests/test_conversion/__init__.py
tests/test_conversion/test_rvc2.py
tests/test_conversion/test_rvc2_legacy.py
tests/test_conversion/test_rvc4_fp16.py
tests/test_conversion/test_rvc4_int8.py
hubai_sdk-0.2.0.dist-info/METADATA
hubai_sdk-0.2.0.dist-info/WHEEL
hubai_sdk-0.2.0.dist-info/entry_points.txt
hubai_sdk-0.2.0.dist-info/top_level.txt
hubai_sdk-0.2.0.dist-info/RECORD
