Metadata-Version: 2.4
Name: hubai-sdk
Version: 0.2.0
Summary: SDK for HubAI.
Author-email: Luxonis <support@luxonis.com>
Maintainer-email: Luxonis <support@luxonis.com>
License-Expression: Apache-2.0
Project-URL: repository, https://github.com/luxonis/hubai-sdk
Project-URL: issues, https://github.com/luxonis/hubai-sdk/issues
Keywords: ml,onnx,openvino,nn,ai,embedded
Classifier: Development Status :: 4 - Beta
Classifier: Programming Language :: Python :: 3.10
Classifier: Topic :: Scientific/Engineering :: Artificial Intelligence
Classifier: Topic :: Scientific/Engineering :: Image Processing
Classifier: Topic :: Scientific/Engineering :: Image Recognition
Requires-Python: >=3.10
License-File: LICENSE
Requires-Dist: luxonis-ml[data,nn_archive]
Requires-Dist: keyring
Requires-Dist: requests
Requires-Dist: cyclopts
Requires-Dist: loguru
Requires-Dist: rich
Requires-Dist: packaging
Requires-Dist: onnx
Requires-Dist: psutil
Requires-Dist: pillow
Requires-Dist: posthog
Provides-Extra: dev
Requires-Dist: openapi-python-client; extra == "dev"
Requires-Dist: pytest; extra == "dev"
Requires-Dist: pre-commit; extra == "dev"
Dynamic: license-file
